yellowbrick/__init__.py
yellowbrick/anscombe.py
yellowbrick/base.py
yellowbrick/bestfit.py
yellowbrick/datasaurus.py
yellowbrick/download.py
yellowbrick/draw.py
yellowbrick/exceptions.py
yellowbrick/pipeline.py
yellowbrick/version.py
yellowbrick/classifier/__init__.py
yellowbrick/classifier/base.py
yellowbrick/classifier/class_prediction_error.py
yellowbrick/classifier/classification_report.py
yellowbrick/classifier/confusion_matrix.py
yellowbrick/classifier/prcurve.py
yellowbrick/classifier/rocauc.py
yellowbrick/classifier/threshold.py
yellowbrick/cluster/__init__.py
yellowbrick/cluster/base.py
yellowbrick/cluster/elbow.py
yellowbrick/cluster/icdm.py
yellowbrick/cluster/silhouette.py
yellowbrick/contrib/__init__.py
yellowbrick/contrib/prepredict.py
yellowbrick/contrib/scatter.py
yellowbrick/contrib/wrapper.py
yellowbrick/contrib/classifier/__init__.py
yellowbrick/contrib/classifier/boundaries.py
yellowbrick/contrib/missing/__init__.py
yellowbrick/contrib/missing/bar.py
yellowbrick/contrib/missing/base.py
yellowbrick/contrib/missing/dispersion.py
yellowbrick/contrib/statsmodels/__init__.py
yellowbrick/contrib/statsmodels/base.py
yellowbrick/datasets/__init__.py
yellowbrick/datasets/base.py
yellowbrick/datasets/download.py
yellowbrick/datasets/loaders.py
yellowbrick/datasets/manifest.json
yellowbrick/datasets/path.py
yellowbrick/datasets/signature.py
yellowbrick/features/__init__.py
yellowbrick/features/base.py
yellowbrick/features/decomposition.py
yellowbrick/features/jointplot.py
yellowbrick/features/manifold.py
yellowbrick/features/pca.py
yellowbrick/features/pcoords.py
yellowbrick/features/projection.py
yellowbrick/features/radviz.py
yellowbrick/features/rankd.py
yellowbrick/gridsearch/__init__.py
yellowbrick/gridsearch/base.py
yellowbrick/gridsearch/pcolor.py
yellowbrick/model_selection/__init__.py
yellowbrick/model_selection/cross_validation.py
yellowbrick/model_selection/dropping_curve.py
yellowbrick/model_selection/importances.py
yellowbrick-1.5.dist-info/LICENSE.txt
yellowbrick-1.5.dist-info/METADATA
yellowbrick-1.5.dist-info/WHEEL
yellowbrick-1.5.dist-info/entry_points.txt
yellowbrick-1.5.dist-info/top_level.txt
yellowbrick-1.5.dist-info/RECORD
