Metadata-Version: 2.1
Name: yellowbrick
Version: 1.5
Summary: A suite of visual analysis and diagnostic tools for machine learning.
Home-page: http://scikit-yb.org/
Author: The scikit-yb developers
Author-email: yellowbrick@googlegroups.com
Maintainer: The scikit-yb developers
Maintainer-email: yellowbrick@googlegroups.com
License: Apache 2
Download-URL: https://github.com/DistrictDataLabs/yellowbrick/tarball/v1.5
Project-URL: Documentation, http://scikit-yb.org/
Project-URL: Download, https://github.com/DistrictDataLabs/yellowbrick/tarball/v1.5
Project-URL: Source, https://github.com/DistrictDataLabs/yellowbrick
Project-URL: Tracker, https://github.com/DistrictDataLabs/yellowbrick/issues
Keywords: visualization,machine learning,scikit-learn,matplotlib,data science
Platform: UNKNOWN
Classifier: Development Status :: 5 - Production/Stable
Classifier: Intended Audience :: Developers
Classifier: Intended Audience :: Science/Research
Classifier: License :: OSI Approved :: Apache Software License
Classifier: Natural Language :: English
Classifier: Operating System :: OS Independent
Classifier: Programming Language :: Python
Classifier: Programming Language :: Python :: 3.5
Classifier: Programming Language :: Python :: 3.6
Classifier: Programming Language :: Python :: 3.7
Classifier: Programming Language :: Python :: 3.8
Classifier: Programming Language :: Python :: 3.9
Classifier: Topic :: Software Development
Classifier: Topic :: Software Development :: Libraries :: Python Modules
Classifier: Topic :: Scientific/Engineering :: Visualization
Requires-Python: >=3.4, <4
License-File: LICENSE.txt
